echo_endpoints/__init__.py
echo_endpoints/echo_endpoints.py
echo_endpoints-0.0.5.dist-info/LICENSE
echo_endpoints-0.0.5.dist-info/METADATA
echo_endpoints-0.0.5.dist-info/WHEEL
echo_endpoints-0.0.5.dist-info/top_level.txt
echo_endpoints-0.0.5.dist-info/RECORD
