Metadata-Version: 2.1
Name: echo_endpoints
Version: 0.0.5
Summary: Requests formatter
Author-email: JHEAminoff <jheaminoff@gmail.com>
Classifier: Programming Language :: Python :: 3
Classifier: License :: OSI Approved :: MIT License
Classifier: Operating System :: OS Independent
Requires-Python: >=3.8
License-File: LICENSE
Requires-Dist: requests
